<?xml version="1.0"?>
<Historical_data_Ahli_Bank><station4><date_19-05><lowStp>750.225</lowStp><highStp>1068.0204081633</highStp></date_19-05><date_20-05><lowStp>786.85714285714</lowStp><highStp>1063.3888888889</highStp></date_20-05><date_21-05><lowStp>741.3488372093</lowStp><highStp>1068.7804878049</highStp></date_21-05><date_22-05><lowStp>784.1875</lowStp><highStp>1062.487804878</highStp></date_22-05><date_23-05><lowStp>794.30303030303</lowStp><highStp>1068.2058823529</highStp></date_23-05><date_24-05><lowStp>785.14285714286</lowStp><highStp>1067.487804878</highStp></date_24-05><date_25-05><lowStp>770.55263157895</lowStp><highStp>1064.875</highStp></date_25-05><date_26-05><lowStp>796.46153846154</lowStp><highStp>1063.4523809524</highStp></date_26-05><date_27-05><lowStp>764.93617021277</lowStp><highStp>1069.375</highStp></date_27-05><date_28-05><lowStp>753.28571428571</lowStp><highStp>1062.9736842105</highStp></date_28-05><date_29-05><lowStp>758.58333333333</lowStp><highStp>1060.3902439024</highStp></date_29-05><date_30-05><lowStp>747.64864864865</lowStp><highStp>1061.6666666667</highStp></date_30-05><date_31-05><lowStp>757.75</lowStp><highStp>1061.2941176471</highStp></date_31-05><date_01-06><lowStp>776.30769230769</lowStp><highStp>1067.6976744186</highStp></date_01-06><date_02-06><lowStp>751.67441860465</lowStp><highStp>1063.4864864865</highStp></date_02-06><date_03-06><lowStp></lowStp><highStp></highStp></date_03-06><date_04-06><lowStp>773.71052631579</lowStp><highStp>1062.225</highStp></date_04-06><date_05-06><lowStp>762.23255813953</lowStp><highStp>1067.8333333333</highStp></date_05-06><date_06-06><lowStp>748.47619047619</lowStp><highStp>1063.8163265306</highStp></date_06-06><date_07-06><lowStp>783.15217391304</lowStp><highStp>1065.8285714286</highStp></date_07-06><date_08-06><lowStp>768.05882352941</lowStp><highStp>1065.0975609756</highStp></date_08-06><date_09-06><lowStp>741.68</lowStp><highStp>1068.4054054054</highStp></date_09-06><date_10-06><lowStp>780.74358974359</lowStp><highStp>1066.5</highStp></date_10-06><date_11-06><lowStp>752.34090909091</lowStp><highStp>1060.55</highStp></date_11-06><date_12-06><lowStp>760.27659574468</lowStp><highStp>1066.3170731707</highStp></date_12-06><date_13-06><lowStp>758</lowStp><highStp>1061.4146341463</highStp></date_13-06><date_14-06><lowStp>776.5</lowStp><highStp>1060.9347826087</highStp></date_14-06><date_15-06><lowStp>819.89285714286</lowStp><highStp>1061.68</highStp></date_15-06></station4></Historical_data_Ahli_Bank>
